git_keeper_server-1.2.0.dist-info/licenses/LICENSE
gkeepserver/__init__.py
gkeepserver/assignments.py
gkeepserver/check_config.py
gkeepserver/check_system.py
gkeepserver/database.py
gkeepserver/directory_locks.py
gkeepserver/email_sender_thread.py
gkeepserver/event_handler.py
gkeepserver/event_handler_assigner.py
gkeepserver/event_handler_thread.py
gkeepserver/faculty.py
gkeepserver/file_writing.py
gkeepserver/generate_password.py
gkeepserver/gkeepd.py
gkeepserver/gkeepd_logger.py
gkeepserver/handler_utils.py
gkeepserver/info_update_thread.py
gkeepserver/initialize_log.py
gkeepserver/local_log_file_reader.py
gkeepserver/log_polling.py
gkeepserver/new_submission_queue.py
gkeepserver/reports.py
gkeepserver/server_configuration.py
gkeepserver/server_email.py
gkeepserver/submission.py
gkeepserver/submission_test_thread.py
gkeepserver/user_setup.py
gkeepserver/version.py
gkeepserver/data/Dockerfile
gkeepserver/data/add_ssh_id
gkeepserver/data/exec
gkeepserver/data/exit
gkeepserver/data/go
gkeepserver/data/post-receive
gkeepserver/data/pre-receive
gkeepserver/data/run_action.sh
gkeepserver/event_handlers/__init__.py
gkeepserver/event_handlers/admin_demote_handler.py
gkeepserver/event_handlers/admin_promote_handler.py
gkeepserver/event_handlers/check_handler.py
gkeepserver/event_handlers/class_add_handler.py
gkeepserver/event_handlers/class_status_handler.py
gkeepserver/event_handlers/delete_handler.py
gkeepserver/event_handlers/disable_handler.py
gkeepserver/event_handlers/faculty_add_handler.py
gkeepserver/event_handlers/handler_registry.py
gkeepserver/event_handlers/passwd_handler.py
gkeepserver/event_handlers/publish_handler.py
gkeepserver/event_handlers/resend_handler.py
gkeepserver/event_handlers/students_add_handler.py
gkeepserver/event_handlers/students_modify_handler.py
gkeepserver/event_handlers/students_remove_handler.py
gkeepserver/event_handlers/submission_handler.py
gkeepserver/event_handlers/trigger_handler.py
gkeepserver/event_handlers/update_handler.py
gkeepserver/event_handlers/upload_handler.py
git_keeper_server-1.2.0.dist-info/METADATA
git_keeper_server-1.2.0.dist-info/WHEEL
git_keeper_server-1.2.0.dist-info/entry_points.txt
git_keeper_server-1.2.0.dist-info/top_level.txt
git_keeper_server-1.2.0.dist-info/RECORD
